quara/LICENSE
quara/__init__.py
quara/settings.py
quara/data_analysis/__init__.py
quara/data_analysis/computation_time.py
quara/data_analysis/data_analysis.py
quara/data_analysis/physicality_violation_check.py
quara/interface/__init__.py
quara/interface/cvxpy/__init__.py
quara/interface/cvxpy/api.py
quara/interface/cvxpy/conversion.py
quara/interface/cvxpy/qtomography/__init__.py
quara/interface/cvxpy/qtomography/standard/__init__.py
quara/interface/cvxpy/qtomography/standard/estimator.py
quara/interface/cvxpy/qtomography/standard/loss_function.py
quara/interface/cvxpy/qtomography/standard/minimization_algorithm.py
quara/interface/forest/__init__.py
quara/interface/forest/api.py
quara/interface/forest/conversion.py
quara/interface/qulacs/__init__.py
quara/interface/qulacs/conversion.py
quara/interface/qutip/__init__.py
quara/interface/qutip/api.py
quara/interface/qutip/conversion.py
quara/interface/qutip/qutip_gate_typical.py
quara/interface/qutip/qutip_povm_typical.py
quara/interface/qutip/qutip_state_typical.py
quara/loss_function/__init__.py
quara/loss_function/loss_function.py
quara/loss_function/mean_squared_error.py
quara/loss_function/probability_based_loss_function.py
quara/loss_function/simple_quadratic_loss_function.py
quara/loss_function/standard_qtomography_based_weighted_probability_based_squared_error.py
quara/loss_function/standard_qtomography_based_weighted_relative_entropy.py
quara/loss_function/weighted_probability_based_squared_error.py
quara/loss_function/weighted_relative_entropy.py
quara/math/__init__.py
quara/math/entropy.py
quara/math/func_proj.py
quara/math/matrix.py
quara/math/norm.py
quara/math/probability.py
quara/minimization_algorithm/__init__.py
quara/minimization_algorithm/minimization_algorithm.py
quara/minimization_algorithm/projected_fast_iterative_shrinkage_thresholding_algorithm.py
quara/minimization_algorithm/projected_gradient_descent.py
quara/minimization_algorithm/projected_gradient_descent_backtracking.py
quara-0.3.0.dist-info/LICENSE
quara-0.3.0.dist-info/METADATA
quara-0.3.0.dist-info/WHEEL
quara-0.3.0.dist-info/top_level.txt
quara-0.3.0.dist-info/RECORD
