Metadata-Version: 2.1
Name: quara
Version: 0.3.0
Summary: Quara, which stands for "Quantum Characterization", is an open-source library for characterizing elementary quantum operations.
Home-page: https://github.com/tknrsgym/quara
Author: Takanori Sugiyama
Author-email: quara@googlegroups.com
License: Apache License 2.0
Keywords: quantum computing,quantum information,quantum characterization,quantum tomography,quara
Platform: UNKNOWN
Classifier: Programming Language :: Python :: 3
Classifier: Programming Language :: Python :: 3.7
Classifier: Programming Language :: Python :: 3.8
Classifier: Programming Language :: Python :: 3.9
Classifier: Topic :: Scientific/Engineering :: Physics
Classifier: Development Status :: 2 - Pre-Alpha
Classifier: Intended Audience :: Science/Research
Classifier: Intended Audience :: Education
Classifier: Operating System :: MacOS :: MacOS X
Classifier: Operating System :: Microsoft :: Windows :: Windows 10
Requires-Python: >=3.7
Requires-Dist: numpy
Requires-Dist: scipy
Requires-Dist: pandas
Requires-Dist: tqdm
Requires-Dist: plotly
Requires-Dist: plotly-express
Requires-Dist: joblib
Requires-Dist: reportlab (==3.6.6)
Requires-Dist: xhtml2pdf
Requires-Dist: psutil
Requires-Dist: kaleido (<=0.1.0.post1,>=0.1.0)
Requires-Dist: jinja2
